instru/__init__.py
instru/config.py
instru/keys.py
instru/shared_doc.py
instru/client/__init__.py
instru/client/base.py
instru/client/coroutine_35.py
instru/client/coroutine_37.py
instru/client/database.py
instru/database/__init__.py
instru/database/base.py
instru/database/config_parser.py
instru/database/config_parser_old.py
instru/database/db.py
instru/functions/__init__.py
instru/functions/io.py
instru/functions/log.py
instru/functions/publisher.py
instru/interface/__init__.py
instru/interface/ipy.py
instru/interface/linker.py
instru/interface/qt.py
instru/objects/__init__.py
instru/objects/base.py
instru/objects/command.py
instru/objects/device.py
instru/objects/parameter.py
instru/objects/parser.py
instru/objects/process.py
instru/objects/system.py
instru/process/__init__.py
instru/process/base.py
instru/process/db.py
instru/process/log.py
instru/process/simulator.py
instru/process/thread.py
instru/server/__init__.py
instru/server/coroutine_35.py
instru/server/coroutine_37.py
instru_client/__init__.py
instru_client/base.py
instru_client/clien_image.py
instru_client/client_image.py
instru_client/coroutine_35.py
instru_client/coroutine_37.py
instru_client/database.py
instru_client/tools.py
instru_server/__init__.py
instru_server/config.py
instru_server/coroutine_35.py
instru_server/coroutine_37.py
instru_server/keys.py
instru_server/database/__init__.py
instru_server/database/base.py
instru_server/database/config_parser.py
instru_server/database/db.py
instru_server/database/path.py
instru_server/database/vtypes.py
instru_server/functions/__init__.py
instru_server/functions/io.py
instru_server/functions/log.py
instru_server/functions/publisher.py
instru_server/process/__init__.py
instru_server/process/base.py
instru_server/process/db.py
instru_server/process/log.py
instru_server/process/simulator.py
instru_server/process/thread.py
instru_server/server/__init__.py
instru_server/server/coroutine_35.py
instru_server/server/coroutine_37.py
instrutools/__init__.py
instrutools-0.5.dev0.dist-info/METADATA
instrutools-0.5.dev0.dist-info/WHEEL
instrutools-0.5.dev0.dist-info/top_level.txt
instrutools-0.5.dev0.dist-info/RECORD
