Metadata-Version: 2.1
Name: instrutools
Version: 0.5.dev0
Summary: UNKNOWN
Home-page: UNKNOWN
Author: Sylvain Guieu
Author-email: sylvain.guieu@univ-grenoble-alpes.fr
License: Creative Commons Attribution-Noncommercial-Share Alike license
Platform: UNKNOWN
Requires-Dist: pyyaml
Requires-Dist: websockets
